Metadata-Version: 2.1
Name: victron
Version: 0.0.5
Summary: An SDK for Victron via Modbus TCP
Home-page: https://gitlab.com/jfk344/python-victron-sdk
Author: @jfk344
Author-email: info@jfk-enterprise.com
License: mit
License-File: LICENSE
